{
  "tesla": "tesla",
  "nvidia": "nvidia",
  "apple": "apple",
  "20": "20",
  "100": "100",
  "5": "5",
  "50": "50",
  "10": "10",
  "google": "google",
  "microsoft": "microsoft",
  "ibm": "IBM",
  "potfolio": "potfolio",
  "orders": "orders",
  "placements": "placements",
  "portfolio": "portfolio",
  "dashboard": "dashboard",
  "profile": "profile",
  "page": "page",
  "articles about trading": "articles about trading",
  "information about stop loss orders": "information about stop loss orders",
  "articles about the importance of diversification in investing": "articles about the importance of diversification in investing",
  "algorithmic trading": "algorithmic trading",
  "candlestick chart patterns": "candlestick chart patterns",
  "the best stocks to invest in for long-term growth ": "the best stocks to invest in for long-term growth ",
  "commodities trading": "commodities trading",
  "technical indicators": "technical indicators",
  "the stock symbol for microsoft": "the stock symbol for Microsoft",
  "the closing price of amazon's stock on friday": "the closing price of Amazon's stock on Friday",
  "the historical stock prices for coca-cola": "the historical stock prices for Coca-Cola",
  "the current stock price for tesla and facebook": "the current stock price for Tesla and Facebook",
  "the stock symbol for alphabet inc": "the stock symbol for Alphabet Inc",
  "the importance of trading": "the importance of trading",
  "news about the cryptocurrency marketrency": "news about the cryptocurrency marketrency",
  "swing trading": "swing trading",
  "articles about the best stocks to invest in for long-term growth": "articles about the best stocks to invest in for long-term growth",
  "the meaning of trading": "the meaning of trading",
  "new articles about the importance of diversification in investing": "new articles about the importance of diversification in investing",
  "articles about the methods of trading": "articles about the methods of trading",
  "videos about diversification in investing": "videos about diversification in investing",
  "portfolio management": "portfolio management",
  "videos about how to trade": "videos about how to trade",
  "closed": "closed",
  "working": "working",
  "new": "new",
  "filled": "filled",
  "paused": "paused",
  "open": "open"
}